odoo/addons/partner_vat_search/README.rst
odoo/addons/partner_vat_search/__init__.py
odoo/addons/partner_vat_search/__manifest__.py
odoo/addons/partner_vat_search/readme/CONTRIBUTORS.md
odoo/addons/partner_vat_search/readme/DESCRIPTION.md
odoo/addons/partner_vat_search/readme/USAGE.md
odoo/addons/partner_vat_search/static/description/icon.png
odoo/addons/partner_vat_search/static/description/index.html
odoo/addons/partner_vat_search/views/res_partner_views.xml
odoo_addon_partner_vat_search-15.0.1.0.0.1.dist-info/METADATA
odoo_addon_partner_vat_search-15.0.1.0.0.1.dist-info/WHEEL
odoo_addon_partner_vat_search-15.0.1.0.0.1.dist-info/top_level.txt
odoo_addon_partner_vat_search-15.0.1.0.0.1.dist-info/RECORD
